{
	"default_api_user": "neoterabyte",
	"default_api_access_token": "1519198601.8409d3e.b670c5891b4a4e0c928b00a1fc40f4a7",
	"cache_prefix": "api:",
	"error_response_code": "422",
	"current_like_subscription_group": "0",
	"paypal_cancel_redirect_uri" : "http://promogram.me/api/payment_cancelled",
	"paypal_success_redirect_uri" : "http://promogram.me/api/payment_success",
	"subscription_price_BRONZE":"19.99",
	"subscription_price_SILVER":"24.99",
	"subscription_price_GOLD":"44.99",
	"paypal_billing_plan_BRONZE":"P-8AM59036150353136MZUAUPA",
	"paypal_billing_plan_SILVER":"P-77L24498VC7973512MZT32MQ",
	"paypal_billing_plan_GOLD":"P-2L084851YX417581VMZTTS2Y",
	"paypal_prod_api" : {
		"mode": "live",
    	"host" : "api.sandbox.paypal.com",
    	"port" : "",            
    	"client_id" : "YOUR TEST CLIENT ID",
    	"client_secret" : "YOUR TEST CLIENT SECRET"
  		},
  	"paypal_sanbox_api" : {
  		"mode": "sandbox",
    	"host" : "api.sandbox.paypal.com",
    	"port" : "",            
    	"client_id" : "AVGalc6X4NaPjw_2E2XS-fcNUgcxgAs84cAJ-sg3F7QLbJ3fVzVhwdKhV0VoQOUV_NG9pmJu-gSqJzOF",
    	"client_secret" : "EGZy2E82nETpmD0Th5jeLV9Udihm3Us-XRY4jka0M7oAPaBo0yZ1KMj0DOn8q3ZmB1DRTK7ZjYX8O3Ks"
  		},
  	"instagram_api" : {
		"instagram_client_id": "8409d3e26cc84366b4527d90fb2bfa7d", 
		"instagram_client_secret": "5c39cec67a0e4cd6993940cc6bf8e942", 
		"instagram_redirect_uri": "http://promogram.me/api/oauth/?user_name=@user_name",
		"instagram_max_media_count": "15"
		}
}
